magnolia/__init__.py
magnolia/main.py
magnolia/commandline/daemon.py
magnolia/tests/__init__.py
magnolia-0.1.0.dist-info/AUTHORS
magnolia-0.1.0.dist-info/LICENSE
magnolia-0.1.0.dist-info/METADATA
magnolia-0.1.0.dist-info/WHEEL
magnolia-0.1.0.dist-info/entry_points.txt
magnolia-0.1.0.dist-info/pbr.json
magnolia-0.1.0.dist-info/top_level.txt
magnolia-0.1.0.dist-info/RECORD
