Metadata-Version: 2.1
Name: magnolia
Version: 0.1.0
Summary: A simple cooperative distributed queuing sysmte
Home-page: https://github.com/shakenfist/magnolia
Author: Michael Still
Author-email: mikal@stillhq.com
License: Apache2
Platform: UNKNOWN
Classifier: Intended Audience :: Information Technology
Classifier: Intended Audience :: System Administrators
Classifier: License :: OSI Approved :: Apache Software License
Classifier: Operating System :: POSIX :: Linux
Classifier: Programming Language :: Python
Classifier: Programming Language :: Python :: 3
Classifier: Programming Language :: Python :: 3.7
Requires-Dist: click (>=8.0.0)
Requires-Dist: flake8
Requires-Dist: testtools
Requires-Dist: tox
